ebase/__init__.py
ebase/script.py
ebase-0.1.1.dist-info/WHEEL
ebase-0.1.1.dist-info/METADATA
ebase-0.1.1.dist-info/RECORD
