Metadata-Version: 2.1
Name: ebase
Version: 0.1.1
Summary: Deta Base engine for essencia organization.
License: MIT
Author: arantesdv
Author-email: arantesdv@me.com
Requires-Python: >=3.7,<4.0
Classifier: License :: OSI Approved :: MIT License
Classifier: Programming Language :: Python :: 3
Classifier: Programming Language :: Python :: 3.7
Classifier: Programming Language :: Python :: 3.8
Classifier: Programming Language :: Python :: 3.9
Requires-Dist: deta (>=1.0.0,<2.0.0)
Requires-Dist: starlette (>=0.16.0,<0.17.0)
